{
	"ACHP": ["69MxIeG","bWIe9H6", false, false],
	"BCHP": ["69MxIeG","bWIe9H6", false, false],
	"ACJK": ["FIouv91", "0dIH1fz", false, false],
	"BCJK": ["FIouv91", "0dIH1fz", false, false],
	"ADNO": ["HSrq6T1", "HSrq6T1", true, true],
	"BDNO": ["HSrq6T1", "HSrq6T1", true, true],
	"ALBT": ["z4GAQr7", "z4GAQr7", false, false],
	"BLBT": ["z4GAQr7", "z4GAQr7", false, false],
	"AOPH": ["Wk6HyGA", "Wk6HyGA", false, false],
	"BOPH": ["Wk6HyGA", "Wk6HyGA", false, false],
	"APOC": ["PGdr64R", "PGdr64R", false, false],
	"BPOC": ["PGdr64R", "PGdr64R", false, false],
	"APRE": ["ojJC5UJ", "S8frDTn", false, false],
	"BPRE": ["ojJC5UJ", "S8frDTn", false, false],
	"APRO": ["wUm5bgh", "Jd7ueGv", false, false],
	"BPRO": ["wUm5bgh", "Jd7ueGv", false, false],
	"ATNW": ["on4rdXm", "WL3Eh6D", false, false],
	"BTNW": ["on4rdXm", "WL3Eh6D", false, false],
	"ATTT": ["uYMoaPE", "uYMoaPE", false, false],
	"BTTT": ["uYMoaPE", "uYMoaPE", false, false],
	"MCOA": ["xq4ICHY", "M7TCdyz", false, false],
	"MCRK": ["pxYvTOi", "akr6qGR", false, false],
	"MCSP": ["QIccriL", "xVA6HJa", false, false],
	"MGGB": ["TAMY9Ur", "vFE57qK", false, false],
	"MPIC": ["oEGw0Ql", "xIyWZ5w", false, false],
	"MSRP": ["1SQIYsB", "7IaTO0O", false, false],
	"MTCJ": ["XQBvL0X", "XQBvL0X", false, false],
	"MTHS": ["oCTk961", "myMxUmS", false, false],
	"RHCP": ["kR83wl9", "md7UXp2", false, false],
	"BHCP": ["kR83wl9", "md7UXp2", false, false],
	"NAW": ["xq4ICHY", "M7TCdyz", false, false],
	"NBAP": ["ruwNAbp", "cSlti7x", false, false],
	"NCLP": ["aTpH8Zu", "i0CVvVm", false, false],
	"NCRD": ["pxYvTOi", "akr6qGR", false, false],
	"NJNG": ["WwPY7wl", "OYl3SLT", false, false],
	"NPIC": ["oEGw0Ql", "xIyWZ5w", false, false],
	"NPXI": ["QIccriL", "xVA6HJa", false, false],
	"NSSP": ["oCTk961", "myMxUmS", false, false]
}